performancefuzzer.py
PerformanceFuzzer-0.0.3.dist-info/LICENSE
PerformanceFuzzer-0.0.3.dist-info/METADATA
PerformanceFuzzer-0.0.3.dist-info/WHEEL
PerformanceFuzzer-0.0.3.dist-info/top_level.txt
PerformanceFuzzer-0.0.3.dist-info/RECORD
