Metadata-Version: 2.1
Name: PerformanceFuzzer
Version: 0.0.3
Summary: PerformanceFuzzer
Home-page: https://github.com/KKimj/PerformanceFuzzer
Author: KKimj
Author-email: kkimj@hanyang.ac.kr
License: GPL-3.0 License
Platform: UNKNOWN
Classifier: Programming Language :: Python :: 3
Classifier: Operating System :: OS Independent
Classifier: Natural Language :: Korean
Requires-Python: >=3
Requires-Dist: numpy
